setup.py
PyRankinity.egg-info/PKG-INFO
PyRankinity.egg-info/SOURCES.txt
PyRankinity.egg-info/dependency_links.txt
PyRankinity.egg-info/requires.txt
PyRankinity.egg-info/top_level.txt
pyrankinity/__init__.py