Metadata-Version: 1.0
Name: PyRankinity
Version: 0.1
Summary: Python Distribution Utilities
Home-page: https://www.github.com/upcounsel/pyrankinity
Author: UpCounsel
Author-email: brad@upcounsel.com
License: MIT
Platform: UNKNOWN
